AUTHORS.md
CMakeLists.txt
LICENSE
MANIFEST.in
README.md
pyproject.toml
setup.cfg
setup.py
docs/Makefile
docs/authors.rst
docs/conf.py
docs/contributing.rst
docs/index.rst
docs/installation.rst
docs/make.bat
docs/readme.rst
docs/usage.rst
docs/_build/html/_static/file.png
docs/_build/html/_static/minus.png
docs/_build/html/_static/plus.png
docs/_build/html/_static/images/logo_colab.png
tests/__init__.py
tests/test_xdr.py
xdrt/__init__.py
xdrt/utils.py
xdrt/xdr_reader.py
xdrt/xvi_reader.py
xdrt.egg-info/PKG-INFO
xdrt.egg-info/SOURCES.txt
xdrt.egg-info/dependency_links.txt
xdrt.egg-info/entry_points.txt
xdrt.egg-info/not-zip-safe
xdrt.egg-info/requires.txt
xdrt.egg-info/top_level.txt
xdrt/cli/__init__.py
xdrt/cli/utils.py
xdrt/cli/xdr.py
xdrt/cli/xvi.py
xdrt/lib/nki_decompression/LICENSE
xdrt/lib/nki_decompression/README.md
xdrt/lib/nki_decompression/nkidecompress.cxx
xdrt/lib/nki_decompression/nkidecompress.h