Metadata-Version: 2.1
Name: xdrt
Version: 0.2.2.dev0
Summary: XDRT (XDR Toolkit) is a python toolkit to work with the Elekta XDR and XVI file formats.
Home-page: https://github.com/NKI-AI/xdrt
Author: Jonas Teuwen
Author-email: j.teuwen@nki.nl
License: Apache Software License 2.0 for the python code, and custom license for the external decoding library.
Keywords: xdrt
Platform: UNKNOWN
Classifier: Development Status :: 2 - Pre-Alpha
Classifier: Intended Audience :: Developers
Classifier: License :: OSI Approved :: Apache Software License
Classifier: Natural Language :: English
Classifier: Programming Language :: Python :: 3.6
Classifier: Programming Language :: Python :: 3.7
Classifier: Programming Language :: Python :: 3.8
Requires-Python: >=3.6
Provides-Extra: dev
